[
  {
    "sps": "fallofthejedi",
    "name-en": "Fall of the Jedi",
    "name-fr": "La chute des Jedi",
    "name-de": "",
    "name-pl": "",
    "name-es": "",
    "icon": "",
    "order": 1
  },
  {
    "sps": "reignoftheempire",
    "name-en": "Reign of the Empire",
    "name-fr": "Le règne de l'Empire",
    "name-de": "",
    "name-pl": "",
    "name-es": "",
    "icon": "",
    "order": 2
  },
  {
    "sps": "ageofrebellion",
    "name-en": "Age of Rebellion",
    "name-fr": "L'âge de la Rébellion",
    "name-de": "",
    "name-pl": "",
    "name-es": "",
    "icon": "",
    "order": 3
  },
  {
    "sps": "thenewrepublic",
    "name-en": "The New Republic",
    "name-fr": "La Nouvelle République",
    "name-de": "",
    "name-pl": "",
    "name-es": "",
    "icon": "",
    "order": 4
  }  
]
